close_numerical_matches/__init__.py
close_numerical_matches/find_matches.py
close_numerical_matches/py.typed
close_numerical_matches/version.py
close_numerical_matches-0.2.3.dist-info/LICENSE
close_numerical_matches-0.2.3.dist-info/METADATA
close_numerical_matches-0.2.3.dist-info/WHEEL
close_numerical_matches-0.2.3.dist-info/top_level.txt
close_numerical_matches-0.2.3.dist-info/RECORD
