Metadata-Version: 2.1
Name: close-numerical-matches
Version: 0.2.3
Summary: Finds close numerical matches across two arrays.
Home-page: https://github.com/shmulvad/close_numerical_matches
Author: Soeren Mulvad
Author-email: Soeren Mulvad <shmulvad@gmail.com>
License: The MIT License (MIT)
Project-URL: Documentation, https://github.com/shmulvad/close_numerical_matches/
Project-URL: Changelog, https://github.com/shmulvad/close_numerical_matches/blob/main/CHANGELOG.md
Project-URL: Homepage, https://github.com/shmulvad/close_numerical_matches/
Project-URL: Github, https://github.com/shmulvad/close_numerical_matches
Project-URL: Source, https://github.com/shmulvad/close_numerical_matches
Project-URL: Issues, https://github.com/shmulvad/close_numerical_matches/issues
Classifier: License :: OSI Approved :: MIT License
Classifier: Programming Language :: Python :: 3.8
Classifier: Programming Language :: Python :: 3.9
Classifier: Programming Language :: Python :: 3.10
Classifier: Programming Language :: Python :: 3.11
Classifier: Programming Language :: Python :: 3.12
Classifier: Topic :: Software Development :: Libraries
Classifier: Typing :: Typed
Requires-Python: >=3.8.0
License-File: LICENSE
Requires-Dist: numpy
